pika/__init__.py
pika/amqp_object.py
pika/callback.py
pika/channel.py
pika/compat.py
pika/connection.py
pika/credentials.py
pika/data.py
pika/delivery_mode.py
pika/diagnostic_utils.py
pika/exceptions.py
pika/exchange_type.py
pika/frame.py
pika/heartbeat.py
pika/spec.py
pika/streamdal.py
pika/tcp_socket_opts.py
pika/validators.py
pika/adapters/__init__.py
pika/adapters/asyncio_connection.py
pika/adapters/base_connection.py
pika/adapters/blocking_connection.py
pika/adapters/gevent_connection.py
pika/adapters/select_connection.py
pika/adapters/tornado_connection.py
pika/adapters/twisted_connection.py
pika/adapters/utils/__init__.py
pika/adapters/utils/connection_workflow.py
pika/adapters/utils/io_services_utils.py
pika/adapters/utils/nbio_interface.py
pika/adapters/utils/selector_ioloop_adapter.py
pika_streamdal/__init__.py
pika_streamdal/amqp_object.py
pika_streamdal/callback.py
pika_streamdal/channel.py
pika_streamdal/compat.py
pika_streamdal/connection.py
pika_streamdal/credentials.py
pika_streamdal/data.py
pika_streamdal/delivery_mode.py
pika_streamdal/diagnostic_utils.py
pika_streamdal/exceptions.py
pika_streamdal/exchange_type.py
pika_streamdal/frame.py
pika_streamdal/heartbeat.py
pika_streamdal/spec.py
pika_streamdal/streamdal.py
pika_streamdal/tcp_socket_opts.py
pika_streamdal/validators.py
pika_streamdal-2.0.0a2.dist-info/LICENSE
pika_streamdal-2.0.0a2.dist-info/METADATA
pika_streamdal-2.0.0a2.dist-info/WHEEL
pika_streamdal-2.0.0a2.dist-info/top_level.txt
pika_streamdal-2.0.0a2.dist-info/zip-safe
pika_streamdal-2.0.0a2.dist-info/RECORD
