Metadata-Version: 2.1
Name: pika_streamdal
Version: 2.0.0a2
Summary: Pika Python AMQP Client Library - Instrumented with Streamdal
Maintainer-email: "Gavin M. Roy" <gavinmroy@gmail.com>, Luke Bakken <lukerbakken@gmail.com>
License: BSD-3-Clause
Project-URL: Homepage, https://pika.readthedocs.io
Project-URL: Source, https://github.com/streamdal/pika-pika
Classifier: Development Status :: 5 - Production/Stable
Classifier: Intended Audience :: Developers
Classifier: License :: OSI Approved :: BSD License
Classifier: Natural Language :: English
Classifier: Operating System :: OS Independent
Classifier: Programming Language :: Python :: 3
Classifier: Programming Language :: Python :: 3.8
Classifier: Programming Language :: Python :: 3.9
Classifier: Programming Language :: Python :: 3.10
Classifier: Programming Language :: Python :: 3.11
Classifier: Programming Language :: Python :: Implementation :: CPython
Classifier: Programming Language :: Python :: Implementation :: Jython
Classifier: Programming Language :: Python :: Implementation :: PyPy
Classifier: Topic :: Communications
Classifier: Topic :: Internet
Classifier: Topic :: Software Development :: Libraries
Classifier: Topic :: Software Development :: Libraries :: Python Modules
Classifier: Topic :: System :: Networking
Requires-Python: >=3.8
License-File: LICENSE
Requires-Dist: streamdal
Provides-Extra: gevent
Requires-Dist: gevent ; extra == 'gevent'
Provides-Extra: tornado
Requires-Dist: tornado ; extra == 'tornado'
Provides-Extra: twisted
Requires-Dist: twisted ; extra == 'twisted'
